Metadata-Version: 1.1
Name: barracks-sdk
Version: 0.0.8
Summary: API implementation for Barracks
Home-page: http://barracks.io
Author: Pierre-Olivier Dybman
Author-email: pod+sdk@barracks.io
License: ALv2
Platform: UNKNOWN
Classifier: Programming Language :: Python
Classifier: License :: OSI Approved
Classifier: Natural Language :: English
Classifier: Operating System :: OS Independent
Classifier: Topic :: Home Automation
Requires: requests
